azure/mgmt/labservices/__init__.py
azure/mgmt/labservices/_configuration.py
azure/mgmt/labservices/_lab_services_client.py
azure/mgmt/labservices/_managed_labs_client.py
azure/mgmt/labservices/_patch.py
azure/mgmt/labservices/_serialization.py
azure/mgmt/labservices/_vendor.py
azure/mgmt/labservices/_version.py
azure/mgmt/labservices/py.typed
azure/mgmt/labservices/aio/__init__.py
azure/mgmt/labservices/aio/_configuration.py
azure/mgmt/labservices/aio/_lab_services_client.py
azure/mgmt/labservices/aio/_managed_labs_client.py
azure/mgmt/labservices/aio/_patch.py
azure/mgmt/labservices/aio/operations/__init__.py
azure/mgmt/labservices/aio/operations/_images_operations.py
azure/mgmt/labservices/aio/operations/_lab_plans_operations.py
azure/mgmt/labservices/aio/operations/_labs_operations.py
azure/mgmt/labservices/aio/operations/_operation_results_operations.py
azure/mgmt/labservices/aio/operations/_operations.py
azure/mgmt/labservices/aio/operations/_patch.py
azure/mgmt/labservices/aio/operations/_schedules_operations.py
azure/mgmt/labservices/aio/operations/_skus_operations.py
azure/mgmt/labservices/aio/operations/_usages_operations.py
azure/mgmt/labservices/aio/operations/_users_operations.py
azure/mgmt/labservices/aio/operations/_virtual_machines_operations.py
azure/mgmt/labservices/models/__init__.py
azure/mgmt/labservices/models/_lab_services_client_enums.py
azure/mgmt/labservices/models/_managed_labs_client_enums.py
azure/mgmt/labservices/models/_models_py3.py
azure/mgmt/labservices/models/_patch.py
azure/mgmt/labservices/operations/__init__.py
azure/mgmt/labservices/operations/_images_operations.py
azure/mgmt/labservices/operations/_lab_plans_operations.py
azure/mgmt/labservices/operations/_labs_operations.py
azure/mgmt/labservices/operations/_operation_results_operations.py
azure/mgmt/labservices/operations/_operations.py
azure/mgmt/labservices/operations/_patch.py
azure/mgmt/labservices/operations/_schedules_operations.py
azure_mgmt_labservices-2.0.0.dist-info/LICENSE
azure_mgmt_labservices-2.0.0.dist-info/METADATA
azure_mgmt_labservices-2.0.0.dist-info/WHEEL
azure_mgmt_labservices-2.0.0.dist-info/top_level.txt
azure_mgmt_labservices-2.0.0.dist-info/RECORD
